[{"Id":37574,"ObjectClassName":"person","ObjectClassId":15,"Left":1158,"Top":137,"Right":1626,"Bottom":1080,"LeftBack":null,"TopBack":null,"RightBack":null,"BottomBack":null,"Confidence":null,"SourceModel":null,"Prediction":null,"PredictionClass":null,"TrackId":null,"Distance":null},{"Id":37575,"ObjectClassName":"person","ObjectClassId":15,"Left":105,"Top":172,"Right":737,"Bottom":1080,"LeftBack":null,"TopBack":null,"RightBack":null,"BottomBack":null,"Confidence":null,"SourceModel":null,"Prediction":null,"PredictionClass":null,"TrackId":null,"Distance":null}]